mapped_pb/__init__.py
mapped_pb/cloud/__init__.py
mapped_pb/cloud/types/__init__.py
mapped_pb/cloud/types/calendar_period_pb2.py
mapped_pb/cloud/types/date_pb2.py
mapped_pb/cloud/types/dayofweek_pb2.py
mapped_pb/cloud/types/geojson_pb2.py
mapped_pb/cloud/types/interval_pb2.py
mapped_pb/cloud/types/metadata_pb2.py
mapped_pb/cloud/types/money_pb2.py
mapped_pb/cloud/types/month_pb2.py
mapped_pb/cloud/types/period_pb2.py
mapped_pb/cloud/types/phone_number_pb2.py
mapped_pb/cloud/types/postal_address_pb2.py
mapped_pb/cloud/types/timeofday_pb2.py
mapped_pb/cloud/types/typed_value_pb2.py
mapped_pb/gateway/__init__.py
mapped_pb/gateway/edgecontrol_pb2.py
mapped_pb/gateway/redispoint_pb2.py
mapped_pb-1.36.14.dist-info/METADATA
mapped_pb-1.36.14.dist-info/WHEEL
mapped_pb-1.36.14.dist-info/RECORD
