Metadata-Version: 2.1
Name: mapped-pb
Version: 1.36.14
Summary: public Mapped Platform Service Definitions using protobuf
Home-page: https://www.mapped.com
License: Apache-2.0
Keywords: mapped,protobuf
Author: Mapped
Author-email: support@mapped.com
Requires-Python: >=3.8,<4.0
Classifier: License :: OSI Approved :: Apache Software License
Classifier: Programming Language :: Python :: 3
Classifier: Programming Language :: Python :: 3.8
Classifier: Programming Language :: Python :: 3.9
Classifier: Programming Language :: Python :: 3.10
Classifier: Programming Language :: Python :: 3.11
Requires-Dist: betterproto (==2.0.0b5)
Requires-Dist: grpclib (==0.4.3)
Project-URL: Repository, https://github.com/mapped/pb
